pfsense_netbox_sync/__init__.py
pfsense_netbox_sync-0.1.0.dist-info/LICENSE.txt
pfsense_netbox_sync-0.1.0.dist-info/METADATA
pfsense_netbox_sync-0.1.0.dist-info/WHEEL
pfsense_netbox_sync-0.1.0.dist-info/entry_points.txt
pfsense_netbox_sync-0.1.0.dist-info/top_level.txt
pfsense_netbox_sync-0.1.0.dist-info/RECORD
