Metadata-Version: 2.2
Name: pfsense-netbox-sync
Version: 0.1.0
Summary: Allows to synchronize NetBox IPAM DNS information to a pfSense instance
Author-email: Aloïs Micard <alois@micard.lu>
Project-URL: Homepage, https://git.creekorful.cloud/creekorful/pfsense-netbox-sync
Project-URL: Issues, https://git.creekorful.cloud/creekorful/pfsense-netbox-sync/issues
Classifier: Programming Language :: Python :: 3
Classifier: Operating System :: OS Independent
Requires-Python: >=3.8
License-File: LICENSE.txt
Requires-Dist: pynetbox>=7.4
Requires-Dist: requests>=2.32
